gh2md/__init__.py
gh2md/gh2md.py
gh2md/templates_markdown.py
gh2md-2.3.1.dist-info/LICENSE
gh2md-2.3.1.dist-info/METADATA
gh2md-2.3.1.dist-info/WHEEL
gh2md-2.3.1.dist-info/entry_points.txt
gh2md-2.3.1.dist-info/top_level.txt
gh2md-2.3.1.dist-info/RECORD
