Metadata-Version: 2.1
Name: gh2md
Version: 2.3.1
Summary: Export Github repository issues to markdown files: https://github.com/mattduck/gh2md.
Home-page: https://github.com/mattduck/gh2md
Author: Matthew Duck
Author-email: matt@mattduck.com
Maintainer: Matthew Duck
Maintainer-email: matt@mattduck.com
License: MIT
Keywords: github,issues,markdown
Classifier: Development Status :: 4 - Beta
Classifier: Intended Audience :: Developers
Classifier: Natural Language :: English
Classifier: License :: OSI Approved :: MIT License
Classifier: Operating System :: OS Independent
Classifier: Programming Language :: Python
Classifier: Programming Language :: Python :: 3.6
Classifier: Programming Language :: Python :: 3.7
Classifier: Programming Language :: Python :: 3.11
Classifier: Programming Language :: Python :: Implementation :: CPython
Classifier: Topic :: Software Development :: Libraries :: Python Modules
License-File: LICENSE
Requires-Dist: six
Requires-Dist: python-dateutil ~=2.8
Requires-Dist: requests ~=2.25
